youku_video_download_mcp/__init__.py
youku_video_download_mcp/__main__.py
youku_video_download_mcp/server.py
youku_video_download_mcp/you_get/__init__.py
youku_video_download_mcp/you_get/common.py
youku_video_download_mcp/you_get/extractor.py
youku_video_download_mcp/you_get/json_output.py
youku_video_download_mcp/you_get/version.py
youku_video_download_mcp/you_get/extractors/__init__.py
youku_video_download_mcp/you_get/extractors/acfun.py
youku_video_download_mcp/you_get/extractors/alive.py
youku_video_download_mcp/you_get/extractors/archive.py
youku_video_download_mcp/you_get/extractors/baidu.py
youku_video_download_mcp/you_get/extractors/bandcamp.py
youku_video_download_mcp/you_get/extractors/baomihua.py
youku_video_download_mcp/you_get/extractors/bigthink.py
youku_video_download_mcp/you_get/extractors/bilibili.py
youku_video_download_mcp/you_get/extractors/bokecc.py
youku_video_download_mcp/you_get/extractors/cbs.py
youku_video_download_mcp/you_get/extractors/ckplayer.py
youku_video_download_mcp/you_get/extractors/cntv.py
youku_video_download_mcp/you_get/extractors/coub.py
youku_video_download_mcp/you_get/extractors/dailymotion.py
youku_video_download_mcp/you_get/extractors/douban.py
youku_video_download_mcp/you_get/extractors/douyin.py
youku_video_download_mcp/you_get/extractors/douyutv.py
youku_video_download_mcp/you_get/extractors/ehow.py
youku_video_download_mcp/you_get/extractors/embed.py
youku_video_download_mcp/you_get/extractors/facebook.py
youku_video_download_mcp/you_get/extractors/fc2video.py
youku_video_download_mcp/you_get/extractors/flickr.py
youku_video_download_mcp/you_get/extractors/freesound.py
youku_video_download_mcp/you_get/extractors/funshion.py
youku_video_download_mcp/you_get/extractors/giphy.py
youku_video_download_mcp/you_get/extractors/google.py
youku_video_download_mcp/you_get/extractors/heavymusic.py
youku_video_download_mcp/you_get/extractors/huomaotv.py
youku_video_download_mcp/you_get/extractors/icourses.py
youku_video_download_mcp-1.0.5.dist-info/METADATA
youku_video_download_mcp-1.0.5.dist-info/WHEEL
youku_video_download_mcp-1.0.5.dist-info/entry_points.txt
youku_video_download_mcp-1.0.5.dist-info/licenses/LICENSE
youku_video_download_mcp-1.0.5.dist-info/RECORD
